pwnd_checker/__init__.py
pwnd_checker/breached_passwd.py
pwnd_checker/main.py
pwnd_checker-0.0.1.dist-info/LICENSE
pwnd_checker-0.0.1.dist-info/METADATA
pwnd_checker-0.0.1.dist-info/WHEEL
pwnd_checker-0.0.1.dist-info/entry_points.txt
pwnd_checker-0.0.1.dist-info/top_level.txt
pwnd_checker-0.0.1.dist-info/RECORD
